dots/__init__.py
dots/__main__.py
dots/context.py
dots/dottools.py
dots/config/__init__.py
dots/config/builder.py
dots/config/config.py
dots/config/ignored.py
dots/plugins/__init__.py
dots/plugins/dir.py
dots/plugins/file.py
dots/plugins/generate.py
dots/plugins/plugin.py
dots/plugins/shellrc.py
dots/util/__init__.py
dots/util/colors.py
dots/util/diff.py
dots/util/env.py
dots/util/fs.py
dots/util/logger.py
dots/util/tools.py
dots/yaml/enrich.py
dots/yaml/loader.py
dots/yaml/merge.py
idzhiblavi_dottools-0.1.9.dist-info/LICENSE
idzhiblavi_dottools-0.1.9.dist-info/METADATA
idzhiblavi_dottools-0.1.9.dist-info/WHEEL
idzhiblavi_dottools-0.1.9.dist-info/entry_points.txt
idzhiblavi_dottools-0.1.9.dist-info/top_level.txt
idzhiblavi_dottools-0.1.9.dist-info/RECORD
