Metadata-Version: 2.1
Name: idzhiblavi_dottools
Version: 0.1.9
Summary: Dotfiles massive management tool
Author: Ibragim Dzhiblavi
Author-email: dzhiblavi@gmail.com
Project-URL: Source, https://github.com/dzhiblavi/dottools
License-File: LICENSE
Requires-Dist: Jinja2 >=3.1.3
Requires-Dist: PyYAML >=6.0.1
Requires-Dist: pyyaml-include >=1.3.2
